{
	"info": {
		"_postman_id": "7f26971b-c4c4-4718-a2c4-aabf31386240",
		"name": "Labefy-Maria-Ferro",
		"schema": "https://schema.getpostman.com/json/collection/v2.1.0/collection.json",
		"_exporter_id": "22366134"
	},
	"item": [
		{
			"name": "getAllPlaylists",
			"request": {
				"method": "GET",
				"header": [
					{
						"key": "Authorization",
						"value": "\"maria-ferro-barros\"",
						"type": "text"
					}
				],
				"url": {
					"raw": "https://us-central1-labenu-apis.cloudfunctions.net/labefy/playlists",
					"protocol": "https",
					"host": [
						"us-central1-labenu-apis",
						"cloudfunctions",
						"net"
					],
					"path": [
						"labefy",
						"playlists"
					]
				}
			},
			"response": []
		},
		{
			"name": "searchPlaylist",
			"request": {
				"method": "GET",
				"header": [
					{
						"key": "Authorization",
						"value": "\"maria-ferro-barros\"",
						"type": "text"
					}
				],
				"url": {
					"raw": "https://us-central1-labenu-apis.cloudfunctions.net/labefy/playlists/search?name=Avril",
					"protocol": "https",
					"host": [
						"us-central1-labenu-apis",
						"cloudfunctions",
						"net"
					],
					"path": [
						"labefy",
						"playlists",
						"search"
					],
					"query": [
						{
							"key": "name",
							"value": "Avril"
						}
					]
				}
			},
			"response": []
		},
		{
			"name": "getPlaylistTrack",
			"request": {
				"method": "GET",
				"header": [
					{
						"key": "Authorization",
						"value": "\"maria-ferro-barros\"",
						"type": "text"
					}
				],
				"url": {
					"raw": "https://us-central1-labenu-apis.cloudfunctions.net/labefy/playlists/467b5eec-4b1e-4ded-9bab-56d96d3e9d68/tracks",
					"protocol": "https",
					"host": [
						"us-central1-labenu-apis",
						"cloudfunctions",
						"net"
					],
					"path": [
						"labefy",
						"playlists",
						"467b5eec-4b1e-4ded-9bab-56d96d3e9d68",
						"tracks"
					]
				}
			},
			"response": []
		},
		{
			"name": "createPlaylist",
			"request": {
				"method": "POST",
				"header": [
					{
						"key": "Authorization",
						"value": "\"maria-ferro-barros\"",
						"type": "text"
					}
				],
				"body": {
					"mode": "raw",
					"raw": "",
					"options": {
						"raw": {
							"language": "json"
						}
					}
				},
				"url": {
					"raw": "https://us-central1-labenu-apis.cloudfunctions.net/labefy/playlists",
					"protocol": "https",
					"host": [
						"us-central1-labenu-apis",
						"cloudfunctions",
						"net"
					],
					"path": [
						"labefy",
						"playlists"
					]
				}
			},
			"response": []
		},
		{
			"name": "addTrackToPlaylist",
			"request": {
				"method": "POST",
				"header": [
					{
						"key": "Authorization",
						"value": "\"maria-ferro-barros\"",
						"type": "text"
					}
				],
				"body": {
					"mode": "raw",
					"raw": "{\r\n    \"name\": \"Waiting For You\", \r\n    \"artist\": \"The Aces\",\r\n    \"url\": \"https://www.youtube.com/watch?v=B9fDHlz_A78\"\r\n}",
					"options": {
						"raw": {
							"language": "json"
						}
					}
				},
				"url": {
					"raw": "https://us-central1-labenu-apis.cloudfunctions.net/labefy/playlists/467b5eec-4b1e-4ded-9bab-56d96d3e9d68/tracks",
					"protocol": "https",
					"host": [
						"us-central1-labenu-apis",
						"cloudfunctions",
						"net"
					],
					"path": [
						"labefy",
						"playlists",
						"467b5eec-4b1e-4ded-9bab-56d96d3e9d68",
						"tracks"
					]
				}
			},
			"response": []
		},
		{
			"name": "removeTrackFromPlaylist",
			"request": {
				"method": "DELETE",
				"header": [
					{
						"key": "Authorization",
						"value": "\"maria-ferro-barros\"",
						"type": "text"
					}
				],
				"url": {
					"raw": "https://us-central1-labenu-apis.cloudfunctions.net/labefy/playlists/a5b49858-efaa-45b3-9056-5280a3ab5cb2/tracks/3c724ad1-166a-4acd-a6c5-a674e3fd9017",
					"protocol": "https",
					"host": [
						"us-central1-labenu-apis",
						"cloudfunctions",
						"net"
					],
					"path": [
						"labefy",
						"playlists",
						"a5b49858-efaa-45b3-9056-5280a3ab5cb2",
						"tracks",
						"3c724ad1-166a-4acd-a6c5-a674e3fd9017"
					]
				}
			},
			"response": []
		},
		{
			"name": "deletePlaylist",
			"request": {
				"method": "DELETE",
				"header": [
					{
						"key": "",
						"value": "\"maria-ferro-barros\"",
						"type": "text"
					}
				],
				"url": {
					"raw": "https://us-central1-labenu-apis.cloudfunctions.net/labefy/playlists/:playlistId",
					"protocol": "https",
					"host": [
						"us-central1-labenu-apis",
						"cloudfunctions",
						"net"
					],
					"path": [
						"labefy",
						"playlists",
						":playlistId"
					],
					"variable": [
						{
							"key": "playlistId",
							"value": null
						}
					]
				}
			},
			"response": []
		}
	]
}